{
    "MetaData": {
        "Title": "Cybersecurity Consulting Services",
        "Description": "Cybersecurity Consulting Services Page Description"
    },
    "Banner": {
        "TitleTag": "Cybersecurity Consulting",
        "Title1": "Expert Cybersecurity",
        "Title2": "Consulting Services",
        "BannerBgImage": "",
        "BannerOtherImages": []
    },
   "MobileAppSolutionSection": {
        "Title1": "Comprehensive Cybersecurity Solutions",
        "Title2": "Tailored to Protect Your Business",
        "Paragraph1": "Leading in cybersecurity consulting, we provide expert services tailored to safeguard your business from evolving threats.",
        "Paragraph2": "Our cybersecurity consulting services offer strategic solutions that address your specific security challenges and compliance needs. From risk assessment to incident response, our experts ensure robust protection for your digital assets.",
        "Services": [
            {
                "Title1": "Risk Assessment",
                "Paragraph": "Comprehensive risk assessment services to identify and mitigate cybersecurity risks tailored to your business.",
                "Icon": "",
                "Link": ""
            },
            {
                "Title1": "Incident Response",
                "Paragraph": "Immediate incident response services to minimize the impact of cybersecurity incidents and ensure business continuity.",
                "Icon": "",
                "Link": ""
            },
            {
                "Title1": "Security Audits",
                "Paragraph": "Thorough security audits to assess and enhance your cybersecurity posture and compliance with industry standards.",
                "Icon": "",
                "Link": ""
            },
            {
                "Title1": "Compliance Consulting",
                "Paragraph": "Expert guidance on regulatory compliance requirements and frameworks to ensure your business meets industry standards.",
                "Icon": "",
                "Link": ""
            }
        ]
    },
    "MobileAppSolutionSection2": {
        "Title1": "Proven Consulting Approach",
        "Title2": "Focused on Your Security Needs",
        "Paragraph": "Delivering end-to-end cybersecurity consulting solutions tailored to protect your business from emerging threats and vulnerabilities.",
        "Services": [
            {
                "Title1": "Strategic Advisory",
                "Paragraph": "Strategic guidance and advisory services to develop robust cybersecurity strategies aligned with your business goals.",
                "Icon": "",
                "Link": ""
            },
            {
                "Title1": "Custom Solutions",
                "Paragraph": "Customized cybersecurity solutions to address specific security challenges and protect your critical assets.",
                "Icon": "",
                "Link": ""
            },
            {
                "Title1": "Training and Awareness",
                "Paragraph": "Employee training and awareness programs to promote a security-first culture and mitigate human error risks.",
                "Icon": "",
                "Link": ""
            }
        ]
    },
    "DrivingSection": {
        "TitleTag": "Why Choose Us for Cybersecurity Consulting?",
        "Title1": "Partner with Us for",
        "Title2": "Expert Cybersecurity Consulting",
        "Title3": "Services",
        "Paragraph": "Empowering businesses with robust cybersecurity consulting services that mitigate risks, ensure compliance, and foster trust.",
        "Services": [
            {
                "Paragraph": "Our comprehensive cybersecurity consulting services protect businesses of all sizes from evolving cyber threats.",
                "Link": ""
            },
            {
                "Paragraph": "We provide tailored security solutions that align with your specific business needs and compliance requirements.",
                "Link": ""
            },
            {
                "Paragraph": "Our team of cybersecurity experts delivers proactive services that enhance your security posture and resilience.",
                "Link": ""
            },
            {
                "Paragraph": "We focus on understanding your unique security challenges to create effective and scalable cybersecurity strategies.",
                "Link": ""
            },
            {
                "Paragraph": "Our approach ensures your cybersecurity solutions are adaptive, secure, and compliant with industry standards.",
                "Link": ""
            }
        ]
    },
    "OurSolutionsSection": {
        "Title1": "Our Cybersecurity Approach",
        "Title2": "Tailored Consulting Services",
        "List": [
            {
                "Name": "Providing end-to-end cybersecurity consulting solutions that safeguard your business against threats."
            },
            {
                "Name": "Offering customized security assessments and solutions to protect your critical data and assets."
            },
            {
                "Name": "Ensuring compliance with industry regulations and standards through expert cybersecurity consulting."
            },
            {
                "Name": "Delivering strategic advisory and training services to build a resilient cybersecurity framework."
            },
            {
                "Name": "Partnering with businesses to enhance cybersecurity resilience and mitigate risks effectively."
            }
        ]
    },
   "RecentWorkSection": {
        "Title1": "Explore Our",
        "Title2": "Recent Cybersecurity Projects",
        "Paragraph": "Our cybersecurity consulting services have enabled businesses to implement robust security measures and protect against cyber threats.",
        "Projects": [
            {
                "ProjectName": "Project Delta",
                "Paragraph": "Implemented a comprehensive cybersecurity strategy that enhanced data protection and compliance.",
                "Image": "https://example.com/project-delta-image.svg",
                "Link": "project-delta-link"
            },
            {
                "ProjectName": "Project Epsilon",
                "Paragraph": "Conducted security audits and provided tailored solutions to strengthen client defenses against cyber attacks.",
                "Image": "https://example.com/project-epsilon-image.svg",
                "Link": "project-epsilon-link"
            },
            {
                "ProjectName": "Project Zeta",
                "Paragraph": "Developed incident response plans and provided training to mitigate cybersecurity risks effectively.",
                "Image": "https://example.com/project-zeta-image.svg",
                "Link": "project-zeta-link"
            }
        ]
    }
}
